server/__init__.py
server/add_user.py
server/config_window.py
server/core.py
server/main_window.py
server/remove_user.py
server/run_server.py
server/server_database.py
server/stat_window.py
server/common/__init__.py
server/common/decorators.py
server/common/descriptors.py
server/common/errors.py
server/common/metaclasses.py
server/common/utils.py
server/common/variables.py
server/logs/__init__.py
server/logs/client_log_config.py
server/logs/server_log_config.py
simple_socket_chat_server-0.1.2.data/scripts/server_run
simple_socket_chat_server-0.1.2.dist-info/METADATA
simple_socket_chat_server-0.1.2.dist-info/WHEEL
simple_socket_chat_server-0.1.2.dist-info/top_level.txt
simple_socket_chat_server-0.1.2.dist-info/RECORD
