Metadata-Version: 2.1
Name: simple-socket-chat-server
Version: 0.1.2
Summary: Simple Socket Chat Server
Home-page: UNKNOWN
Author: Ilya Zaytsev
Author-email: intiguan@gmail.com
License: UNKNOWN
Platform: UNKNOWN
Requires-Dist: PyQt5
Requires-Dist: sqlalchemy
Requires-Dist: pycryptodome
Requires-Dist: pycryptodomex
